{
  "schema_version": 1,
  "updated_at": 1782383167.6047869,
  "kind": "recording",
  "source_id": "20260624_232930_white_to_k4",
  "frame": 57,
  "label": "empty",
  "note": "",
  "image": "frames/wrist/000057.jpg",
  "image_shape": {
    "width": 1920,
    "height": 1080
  },
  "timestamp": 1782336575.995924,
  "elapsed_s": 5.980067014694214,
  "gripper_position": {
    "follower": {
      "value": 5.27,
      "unit": "%",
      "min_value": 0.0,
      "max_value": 100.0
    },
    "leader": {
      "value": 4.68,
      "unit": "%",
      "min_value": 0.0,
      "max_value": 100.0
    }
  },
  "joints": {
    "follower": {
      "shoulder_pan": {
        "value": -50.11,
        "unit": "deg",
        "min_value": -180.0,
        "max_value": 180.0
      },
      "shoulder_lift": {
        "value": -5.67,
        "unit": "deg",
        "min_value": -180.0,
        "max_value": 180.0
      },
      "elbow_flex": {
        "value": 42.51,
        "unit": "deg",
        "min_value": -180.0,
        "max_value": 180.0
      },
      "wrist_flex": {
        "value": 36.35,
        "unit": "deg",
        "min_value": -180.0,
        "max_value": 180.0
      },
      "wrist_roll": {
        "value": -10.51,
        "unit": "deg",
        "min_value": -180.0,
        "max_value": 180.0
      },
      "gripper": {
        "value": 5.27,
        "unit": "%",
        "min_value": 0.0,
        "max_value": 100.0
      }
    },
    "leader": {
      "shoulder_pan": {
        "value": -48.88,
        "unit": "deg",
        "min_value": -180.0,
        "max_value": 180.0
      },
      "shoulder_lift": {
        "value": -5.54,
        "unit": "deg",
        "min_value": -180.0,
        "max_value": 180.0
      },
      "elbow_flex": {
        "value": 40.13,
        "unit": "deg",
        "min_value": -180.0,
        "max_value": 180.0
      },
      "wrist_flex": {
        "value": 34.11,
        "unit": "deg",
        "min_value": -180.0,
        "max_value": 180.0
      },
      "wrist_roll": {
        "value": -10.59,
        "unit": "deg",
        "min_value": -180.0,
        "max_value": 180.0
      },
      "gripper": {
        "value": 4.68,
        "unit": "%",
        "min_value": 0.0,
        "max_value": 100.0
      }
    }
  },
  "detector": {
    "holding": false,
    "color": null,
    "confidence": 1.0,
    "circle": null,
    "reason": "follower gripper 5.27% outside held range 1.00-2.00%"
  },
  "created_at": 1782383167.6047869,
  "image_detector": {
    "holding": true,
    "color": "white",
    "confidence": 0.8144892493688143,
    "circle": {
      "x": 813.0,
      "y": 288.0,
      "radius": 57.0
    },
    "reason": "L=175.9 S=11.3 stdL=7.9"
  }
}
